gitem/__init__.py
gitem/__main__.py
gitem/analytics.py
gitem/api.py
gitem/output/__init__.py
gitem/output/base.py
gitem/output/json.py
gitem/output/stdout.py
gitem-0.9.2.dist-info/LICENSE
gitem-0.9.2.dist-info/METADATA
gitem-0.9.2.dist-info/WHEEL
gitem-0.9.2.dist-info/entry_points.txt
gitem-0.9.2.dist-info/top_level.txt
gitem-0.9.2.dist-info/RECORD
